gym_snake/__init__.py
gym_snake/envs/__init__.py
gym_snake/envs/snake_env.py
gym_snake-0.1.7.dist-info/LICENSE
gym_snake-0.1.7.dist-info/METADATA
gym_snake-0.1.7.dist-info/WHEEL
gym_snake-0.1.7.dist-info/top_level.txt
gym_snake-0.1.7.dist-info/RECORD
