Metadata-Version: 2.1
Name: gym-snake
Version: 0.1.7
Summary: Gym Snake Env
Home-page: https://github.com/boangri/gym-snake
Author: Boris Gribovskiy
Author-email: xinu@yandex.ru
License: MIT License
Platform: UNKNOWN
Requires-Python: >=3.6
Requires-Dist: gym
Requires-Dist: numpy
Requires-Dist: pygame
